detectron2_layers/__init__.py
detectron2_layers/batch_norm.py
detectron2_layers/blocks.py
detectron2_layers/utils.py
detectron2_layers/wrappers.py
detectron2_layers-0.0.5.dist-info/METADATA
detectron2_layers-0.0.5.dist-info/WHEEL
detectron2_layers-0.0.5.dist-info/top_level.txt
detectron2_layers-0.0.5.dist-info/RECORD
