Metadata-Version: 2.1
Name: detectron2-layers
Version: 0.0.5
Summary: A replacement for detectron2.layers, specifically for use by SegGPT.
Author: Andrew Healey
Author-email: doolie.healey@gmail.com
License: Apache
Requires-Dist: fvcore
Requires-Dist: torch
